hylaa/__init__.py
hylaa/_version.py
hylaa/aggdag.py
hylaa/aggregate.py
hylaa/aggstrat.py
hylaa/check_trace.py
hylaa/core.py
hylaa/deaggregation.py
hylaa/guard_opt_data.py
hylaa/hybrid_automaton.py
hylaa/kamenev.py
hylaa/lpinstance.py
hylaa/lpplot.py
hylaa/lputil.py
hylaa/plotutil.py
hylaa/result.py
hylaa/settings.py
hylaa/simulation.py
hylaa/stateset.py
hylaa/symbolic.py
hylaa/time_elapse.py
hylaa/time_elapse_expm.py
hylaa/timerutil.py
hylaa/util.py
hylaa-2.0.2.dist-info/LICENSE
hylaa-2.0.2.dist-info/METADATA
hylaa-2.0.2.dist-info/WHEEL
hylaa-2.0.2.dist-info/top_level.txt
hylaa-2.0.2.dist-info/RECORD
