Metadata-Version: 2.1
Name: hylaa
Version: 2.0.2
Summary: Hylaa
Home-page: https://github.com/stanleybak/hylaa
Author: Stanley Bak
Author-email: bak2007-DONTSENDMEEMAIL@gmail.com
License: GPLv3
Classifier: Programming Language :: Python :: 3
Classifier: License :: OSI Approved :: GNU General Public License v3 (GPLv3)
Classifier: Operating System :: OS Independent
Classifier: Topic :: Scientific/Engineering :: Artificial Intelligence
Classifier: Intended Audience :: Science/Research
Classifier: Topic :: Scientific/Engineering
License-File: LICENSE
Requires-Dist: ffmpeg-python
Requires-Dist: pytest
Requires-Dist: numpy
Requires-Dist: scipy
Requires-Dist: sympy
Requires-Dist: matplotlib
Requires-Dist: termcolor
Requires-Dist: swiglpk
Requires-Dist: graphviz
